README.rst
setup.cfg
setup.py
fracpy/__init__.py
fracpy/colors.py
fracpy/fracpy.c
fracpy/fractals.c
fracpy/point.c
fracpy.egg-info/PKG-INFO
fracpy.egg-info/SOURCES.txt
fracpy.egg-info/dependency_links.txt
fracpy.egg-info/requires.txt
fracpy.egg-info/top_level.txt