Metadata-Version: 1.0
Name: fracpy
Version: 0.0.1
Summary: Fractal library
Home-page: UNKNOWN
Author: Borodin Gregory
Author-email: grihabor@mail.ru
License: MIT
Platform: UNKNOWN
